{"header":{"xyz":{"source":[],"mosaic":false},"page":211,"raw":{"soiltest_result":"0","bbox":"57.598333,109.544722,1.933333,163.806111","page":"211"},"conditions":{"soiltest_result":0,"north":57.598333,"west":109.544722,"south":1.933333,"east":163.806111},"success":true,"message":""},"data":{"meta":{"total":212844,"page":211,"pages":7095,"count":30},"values":[{"id":578912,"code":"NGIC202206144-0028","latitude":"36.508888888889","longitude":"138.11333333333","source_code":"","project_name":"\u4fe1\u6fc3\u5ddd\u6c34\u7cfb\u5343\u66f2\u5ddd\u904a\u6c34\u5730\u4e8b\u696d","survey_name":"\u4ee4\u548c4\u5e74\u5ea6\u5343\u66f2\u5ddd\u904a\u6c34\u5730\u5730\u8cea\u8abf\u67fb\u696d\u52d9","client_name":"\u56fd\u571f\u4ea4\u901a\u7701\u5317\u9678\u5730\u65b9\u6574\u5099\u5c40\u5343\u66f2\u5ddd\u6cb3\u5ddd\u4e8b\u52d9\u6240","boring_xml_url":47,"boring_view_url":1,"soilmap_view_url":null,"soiltest_xml_url":47,"soiltest_view_url":47},{"id":578911,"code":"NGIC202206144-0027","latitude":"36.510891666667","longitude":"138.11186388889","source_code":"","project_name":"\u4fe1\u6fc3\u5ddd\u6c34\u7cfb\u5343\u66f2\u5ddd\u904a\u6c34\u5730\u4e8b\u696d","survey_name":"\u4ee4\u548c4\u5e74\u5ea6\u5343\u66f2\u5ddd\u904a\u6c34\u5730\u5730\u8cea\u8abf\u67fb\u696d\u52d9","client_name":"\u56fd\u571f\u4ea4\u901a\u7701\u5317\u9678\u5730\u65b9\u6574\u5099\u5c40\u5343\u66f2\u5ddd\u6cb3\u5ddd\u4e8b\u52d9\u6240","boring_xml_url":47,"boring_view_url":1,"soilmap_view_url":null,"soiltest_xml_url":47,"soiltest_view_url":47},{"id":578910,"code":"NGIC202206144-0026","latitude":"36.510952777778","longitude":"138.11199166667","source_code":"","project_name":"\u4fe1\u6fc3\u5ddd\u6c34\u7cfb\u5343\u66f2\u5ddd\u904a\u6c34\u5730\u4e8b\u696d","survey_name":"\u4ee4\u548c4\u5e74\u5ea6\u5343\u66f2\u5ddd\u904a\u6c34\u5730\u5730\u8cea\u8abf\u67fb\u696d\u52d9","client_name":"\u56fd\u571f\u4ea4\u901a\u7701\u5317\u9678\u5730\u65b9\u6574\u5099\u5c40\u5343\u66f2\u5ddd\u6cb3\u5ddd\u4e8b\u52d9\u6240","boring_xml_url":47,"boring_view_url":1,"soilmap_view_url":null,"soiltest_xml_url":47,"soiltest_view_url":47},{"id":578909,"code":"NGIC202206144-0025","latitude":"36.511016666667","longitude":"138.11212222222","source_code":"","project_name":"\u4fe1\u6fc3\u5ddd\u6c34\u7cfb\u5343\u66f2\u5ddd\u904a\u6c34\u5730\u4e8b\u696d","survey_name":"\u4ee4\u548c4\u5e74\u5ea6\u5343\u66f2\u5ddd\u904a\u6c34\u5730\u5730\u8cea\u8abf\u67fb\u696d\u52d9","client_name":"\u56fd\u571f\u4ea4\u901a\u7701\u5317\u9678\u5730\u65b9\u6574\u5099\u5c40\u5343\u66f2\u5ddd\u6cb3\u5ddd\u4e8b\u52d9\u6240","boring_xml_url":47,"boring_view_url":1,"soilmap_view_url":null,"soiltest_xml_url":47,"soiltest_view_url":47},{"id":578908,"code":"NGIC202206144-0024","latitude":"36.553286111111","longitude":"138.123825","source_code":"","project_name":"\u4fe1\u6fc3\u5ddd\u6c34\u7cfb\u5343\u66f2\u5ddd\u904a\u6c34\u5730\u4e8b\u696d","survey_name":"\u4ee4\u548c4\u5e74\u5ea6\u5343\u66f2\u5ddd\u904a\u6c34\u5730\u5730\u8cea\u8abf\u67fb\u696d\u52d9","client_name":"\u56fd\u571f\u4ea4\u901a\u7701\u5317\u9678\u5730\u65b9\u6574\u5099\u5c40\u5343\u66f2\u5ddd\u6cb3\u5ddd\u4e8b\u52d9\u6240","boring_xml_url":47,"boring_view_url":1,"soilmap_view_url":null,"soiltest_xml_url":47,"soiltest_view_url":47},{"id":578907,"code":"NGIC202206144-0023","latitude":"36.553288888889","longitude":"138.12406944444","source_code":"","project_name":"\u4fe1\u6fc3\u5ddd\u6c34\u7cfb\u5343\u66f2\u5ddd\u904a\u6c34\u5730\u4e8b\u696d","survey_name":"\u4ee4\u548c4\u5e74\u5ea6\u5343\u66f2\u5ddd\u904a\u6c34\u5730\u5730\u8cea\u8abf\u67fb\u696d\u52d9","client_name":"\u56fd\u571f\u4ea4\u901a\u7701\u5317\u9678\u5730\u65b9\u6574\u5099\u5c40\u5343\u66f2\u5ddd\u6cb3\u5ddd\u4e8b\u52d9\u6240","boring_xml_url":47,"boring_view_url":1,"soilmap_view_url":null,"soiltest_xml_url":47,"soiltest_view_url":47},{"id":578906,"code":"NGIC202206144-0022","latitude":"36.553216666667","longitude":"138.12418888889","source_code":"","project_name":"\u4fe1\u6fc3\u5ddd\u6c34\u7cfb\u5343\u66f2\u5ddd\u904a\u6c34\u5730\u4e8b\u696d","survey_name":"\u4ee4\u548c4\u5e74\u5ea6\u5343\u66f2\u5ddd\u904a\u6c34\u5730\u5730\u8cea\u8abf\u67fb\u696d\u52d9","client_name":"\u56fd\u571f\u4ea4\u901a\u7701\u5317\u9678\u5730\u65b9\u6574\u5099\u5c40\u5343\u66f2\u5ddd\u6cb3\u5ddd\u4e8b\u52d9\u6240","boring_xml_url":47,"boring_view_url":1,"soilmap_view_url":null,"soiltest_xml_url":47,"soiltest_view_url":47},{"id":578905,"code":"NGIC202206144-0021","latitude":"36.809722222222","longitude":"138.35194444444","source_code":"","project_name":"\u4fe1\u6fc3\u5ddd\u6c34\u7cfb\u5343\u66f2\u5ddd\u904a\u6c34\u5730\u4e8b\u696d","survey_name":"\u4ee4\u548c4\u5e74\u5ea6\u5343\u66f2\u5ddd\u904a\u6c34\u5730\u5730\u8cea\u8abf\u67fb\u696d\u52d9","client_name":"\u56fd\u571f\u4ea4\u901a\u7701\u5317\u9678\u5730\u65b9\u6574\u5099\u5c40\u5343\u66f2\u5ddd\u6cb3\u5ddd\u4e8b\u52d9\u6240","boring_xml_url":47,"boring_view_url":1,"soilmap_view_url":null,"soiltest_xml_url":47,"soiltest_view_url":47},{"id":578904,"code":"NGIC202206144-0020","latitude":"36.813888888889","longitude":"138.35277777778","source_code":"","project_name":"\u4fe1\u6fc3\u5ddd\u6c34\u7cfb\u5343\u66f2\u5ddd\u904a\u6c34\u5730\u4e8b\u696d","survey_name":"\u4ee4\u548c4\u5e74\u5ea6\u5343\u66f2\u5ddd\u904a\u6c34\u5730\u5730\u8cea\u8abf\u67fb\u696d\u52d9","client_name":"\u56fd\u571f\u4ea4\u901a\u7701\u5317\u9678\u5730\u65b9\u6574\u5099\u5c40\u5343\u66f2\u5ddd\u6cb3\u5ddd\u4e8b\u52d9\u6240","boring_xml_url":47,"boring_view_url":1,"soilmap_view_url":null,"soiltest_xml_url":47,"soiltest_view_url":47},{"id":578903,"code":"NGIC202206144-0019","latitude":"36.814166666667","longitude":"138.35027777778","source_code":"","project_name":"\u4fe1\u6fc3\u5ddd\u6c34\u7cfb\u5343\u66f2\u5ddd\u904a\u6c34\u5730\u4e8b\u696d","survey_name":"\u4ee4\u548c4\u5e74\u5ea6\u5343\u66f2\u5ddd\u904a\u6c34\u5730\u5730\u8cea\u8abf\u67fb\u696d\u52d9","client_name":"\u56fd\u571f\u4ea4\u901a\u7701\u5317\u9678\u5730\u65b9\u6574\u5099\u5c40\u5343\u66f2\u5ddd\u6cb3\u5ddd\u4e8b\u52d9\u6240","boring_xml_url":47,"boring_view_url":1,"soilmap_view_url":null,"soiltest_xml_url":47,"soiltest_view_url":47},{"id":578902,"code":"NGIC202206144-0018","latitude":"36.815555555556","longitude":"138.35166666667","source_code":"","project_name":"\u4fe1\u6fc3\u5ddd\u6c34\u7cfb\u5343\u66f2\u5ddd\u904a\u6c34\u5730\u4e8b\u696d","survey_name":"\u4ee4\u548c4\u5e74\u5ea6\u5343\u66f2\u5ddd\u904a\u6c34\u5730\u5730\u8cea\u8abf\u67fb\u696d\u52d9","client_name":"\u56fd\u571f\u4ea4\u901a\u7701\u5317\u9678\u5730\u65b9\u6574\u5099\u5c40\u5343\u66f2\u5ddd\u6cb3\u5ddd\u4e8b\u52d9\u6240","boring_xml_url":47,"boring_view_url":1,"soilmap_view_url":null,"soiltest_xml_url":47,"soiltest_view_url":47},{"id":578901,"code":"NGIC202206144-0017","latitude":"36.817222222222","longitude":"138.35138888889","source_code":"","project_name":"\u4fe1\u6fc3\u5ddd\u6c34\u7cfb\u5343\u66f2\u5ddd\u904a\u6c34\u5730\u4e8b\u696d","survey_name":"\u4ee4\u548c4\u5e74\u5ea6\u5343\u66f2\u5ddd\u904a\u6c34\u5730\u5730\u8cea\u8abf\u67fb\u696d\u52d9","client_name":"\u56fd\u571f\u4ea4\u901a\u7701\u5317\u9678\u5730\u65b9\u6574\u5099\u5c40\u5343\u66f2\u5ddd\u6cb3\u5ddd\u4e8b\u52d9\u6240","boring_xml_url":47,"boring_view_url":1,"soilmap_view_url":null,"soiltest_xml_url":47,"soiltest_view_url":47},{"id":578900,"code":"NGIC202206144-0016","latitude":"36.819166666667","longitude":"138.35","source_code":"","project_name":"\u4fe1\u6fc3\u5ddd\u6c34\u7cfb\u5343\u66f2\u5ddd\u904a\u6c34\u5730\u4e8b\u696d","survey_name":"\u4ee4\u548c4\u5e74\u5ea6\u5343\u66f2\u5ddd\u904a\u6c34\u5730\u5730\u8cea\u8abf\u67fb\u696d\u52d9","client_name":"\u56fd\u571f\u4ea4\u901a\u7701\u5317\u9678\u5730\u65b9\u6574\u5099\u5c40\u5343\u66f2\u5ddd\u6cb3\u5ddd\u4e8b\u52d9\u6240","boring_xml_url":47,"boring_view_url":1,"soilmap_view_url":null,"soiltest_xml_url":47,"soiltest_view_url":47},{"id":578899,"code":"NGIC202206144-0015","latitude":"36.821111111111","longitude":"138.35083333333","source_code":"","project_name":"\u4fe1\u6fc3\u5ddd\u6c34\u7cfb\u5343\u66f2\u5ddd\u904a\u6c34\u5730\u4e8b\u696d","survey_name":"\u4ee4\u548c4\u5e74\u5ea6\u5343\u66f2\u5ddd\u904a\u6c34\u5730\u5730\u8cea\u8abf\u67fb\u696d\u52d9","client_name":"\u56fd\u571f\u4ea4\u901a\u7701\u5317\u9678\u5730\u65b9\u6574\u5099\u5c40\u5343\u66f2\u5ddd\u6cb3\u5ddd\u4e8b\u52d9\u6240","boring_xml_url":47,"boring_view_url":1,"soilmap_view_url":null,"soiltest_xml_url":47,"soiltest_view_url":47},{"id":578898,"code":"NGIC202206144-0014","latitude":"36.806944444444","longitude":"138.35555555556","source_code":"","project_name":"\u4fe1\u6fc3\u5ddd\u6c34\u7cfb\u5343\u66f2\u5ddd\u904a\u6c34\u5730\u4e8b\u696d","survey_name":"\u4ee4\u548c4\u5e74\u5ea6\u5343\u66f2\u5ddd\u904a\u6c34\u5730\u5730\u8cea\u8abf\u67fb\u696d\u52d9","client_name":"\u56fd\u571f\u4ea4\u901a\u7701\u5317\u9678\u5730\u65b9\u6574\u5099\u5c40\u5343\u66f2\u5ddd\u6cb3\u5ddd\u4e8b\u52d9\u6240","boring_xml_url":47,"boring_view_url":1,"soilmap_view_url":null,"soiltest_xml_url":47,"soiltest_view_url":47},{"id":578897,"code":"NGIC202206144-0013","latitude":"36.813888888889","longitude":"138.355","source_code":"","project_name":"\u4fe1\u6fc3\u5ddd\u6c34\u7cfb\u5343\u66f2\u5ddd\u904a\u6c34\u5730\u4e8b\u696d","survey_name":"\u4ee4\u548c4\u5e74\u5ea6\u5343\u66f2\u5ddd\u904a\u6c34\u5730\u5730\u8cea\u8abf\u67fb\u696d\u52d9","client_name":"\u56fd\u571f\u4ea4\u901a\u7701\u5317\u9678\u5730\u65b9\u6574\u5099\u5c40\u5343\u66f2\u5ddd\u6cb3\u5ddd\u4e8b\u52d9\u6240","boring_xml_url":47,"boring_view_url":1,"soilmap_view_url":null,"soiltest_xml_url":47,"soiltest_view_url":47},{"id":578896,"code":"NGIC202206144-0012","latitude":"36.814166666667","longitude":"138.35527777778","source_code":"","project_name":"\u4fe1\u6fc3\u5ddd\u6c34\u7cfb\u5343\u66f2\u5ddd\u904a\u6c34\u5730\u4e8b\u696d","survey_name":"\u4ee4\u548c4\u5e74\u5ea6\u5343\u66f2\u5ddd\u904a\u6c34\u5730\u5730\u8cea\u8abf\u67fb\u696d\u52d9","client_name":"\u56fd\u571f\u4ea4\u901a\u7701\u5317\u9678\u5730\u65b9\u6574\u5099\u5c40\u5343\u66f2\u5ddd\u6cb3\u5ddd\u4e8b\u52d9\u6240","boring_xml_url":47,"boring_view_url":1,"soilmap_view_url":null,"soiltest_xml_url":47,"soiltest_view_url":47},{"id":578895,"code":"NGIC202206144-0011","latitude":"36.814166666667","longitude":"138.35555555556","source_code":"","project_name":"\u4fe1\u6fc3\u5ddd\u6c34\u7cfb\u5343\u66f2\u5ddd\u904a\u6c34\u5730\u4e8b\u696d","survey_name":"\u4ee4\u548c4\u5e74\u5ea6\u5343\u66f2\u5ddd\u904a\u6c34\u5730\u5730\u8cea\u8abf\u67fb\u696d\u52d9","client_name":"\u56fd\u571f\u4ea4\u901a\u7701\u5317\u9678\u5730\u65b9\u6574\u5099\u5c40\u5343\u66f2\u5ddd\u6cb3\u5ddd\u4e8b\u52d9\u6240","boring_xml_url":47,"boring_view_url":1,"soilmap_view_url":null,"soiltest_xml_url":47,"soiltest_view_url":47},{"id":578894,"code":"NGIC202206144-0010","latitude":"36.815","longitude":"138.35472222222","source_code":"","project_name":"\u4fe1\u6fc3\u5ddd\u6c34\u7cfb\u5343\u66f2\u5ddd\u904a\u6c34\u5730\u4e8b\u696d","survey_name":"\u4ee4\u548c4\u5e74\u5ea6\u5343\u66f2\u5ddd\u904a\u6c34\u5730\u5730\u8cea\u8abf\u67fb\u696d\u52d9","client_name":"\u56fd\u571f\u4ea4\u901a\u7701\u5317\u9678\u5730\u65b9\u6574\u5099\u5c40\u5343\u66f2\u5ddd\u6cb3\u5ddd\u4e8b\u52d9\u6240","boring_xml_url":47,"boring_view_url":1,"soilmap_view_url":null,"soiltest_xml_url":47,"soiltest_view_url":47},{"id":578893,"code":"NGIC202206144-0009","latitude":"36.8215","longitude":"138.35156111111","source_code":"","project_name":"\u4fe1\u6fc3\u5ddd\u6c34\u7cfb\u5343\u66f2\u5ddd\u904a\u6c34\u5730\u4e8b\u696d","survey_name":"\u4ee4\u548c4\u5e74\u5ea6\u5343\u66f2\u5ddd\u904a\u6c34\u5730\u5730\u8cea\u8abf\u67fb\u696d\u52d9","client_name":"\u56fd\u571f\u4ea4\u901a\u7701\u5317\u9678\u5730\u65b9\u6574\u5099\u5c40\u5343\u66f2\u5ddd\u6cb3\u5ddd\u4e8b\u52d9\u6240","boring_xml_url":47,"boring_view_url":1,"soilmap_view_url":null,"soiltest_xml_url":47,"soiltest_view_url":47},{"id":578892,"code":"NGIC202206144-0008","latitude":"36.821516666667","longitude":"138.351825","source_code":"","project_name":"\u4fe1\u6fc3\u5ddd\u6c34\u7cfb\u5343\u66f2\u5ddd\u904a\u6c34\u5730\u4e8b\u696d","survey_name":"\u4ee4\u548c4\u5e74\u5ea6\u5343\u66f2\u5ddd\u904a\u6c34\u5730\u5730\u8cea\u8abf\u67fb\u696d\u52d9","client_name":"\u56fd\u571f\u4ea4\u901a\u7701\u5317\u9678\u5730\u65b9\u6574\u5099\u5c40\u5343\u66f2\u5ddd\u6cb3\u5ddd\u4e8b\u52d9\u6240","boring_xml_url":47,"boring_view_url":1,"soilmap_view_url":null,"soiltest_xml_url":47,"soiltest_view_url":47},{"id":578891,"code":"NGIC202206144-0007","latitude":"36.821533333333","longitude":"138.35206944444","source_code":"","project_name":"\u4fe1\u6fc3\u5ddd\u6c34\u7cfb\u5343\u66f2\u5ddd\u904a\u6c34\u5730\u4e8b\u696d","survey_name":"\u4ee4\u548c4\u5e74\u5ea6\u5343\u66f2\u5ddd\u904a\u6c34\u5730\u5730\u8cea\u8abf\u67fb\u696d\u52d9","client_name":"\u56fd\u571f\u4ea4\u901a\u7701\u5317\u9678\u5730\u65b9\u6574\u5099\u5c40\u5343\u66f2\u5ddd\u6cb3\u5ddd\u4e8b\u52d9\u6240","boring_xml_url":47,"boring_view_url":1,"soilmap_view_url":null,"soiltest_xml_url":47,"soiltest_view_url":47},{"id":578890,"code":"NGIC202206144-0006","latitude":"36.519166666667","longitude":"138.11361111111","source_code":"","project_name":"\u4fe1\u6fc3\u5ddd\u6c34\u7cfb\u5343\u66f2\u5ddd\u904a\u6c34\u5730\u4e8b\u696d","survey_name":"\u4ee4\u548c4\u5e74\u5ea6\u5343\u66f2\u5ddd\u904a\u6c34\u5730\u5730\u8cea\u8abf\u67fb\u696d\u52d9","client_name":"\u56fd\u571f\u4ea4\u901a\u7701\u5317\u9678\u5730\u65b9\u6574\u5099\u5c40\u5343\u66f2\u5ddd\u6cb3\u5ddd\u4e8b\u52d9\u6240","boring_xml_url":47,"boring_view_url":1,"soilmap_view_url":null,"soiltest_xml_url":47,"soiltest_view_url":47},{"id":578889,"code":"NGIC202206144-0005","latitude":"36.520277777778","longitude":"138.11333333333","source_code":"","project_name":"\u4fe1\u6fc3\u5ddd\u6c34\u7cfb\u5343\u66f2\u5ddd\u904a\u6c34\u5730\u4e8b\u696d","survey_name":"\u4ee4\u548c4\u5e74\u5ea6\u5343\u66f2\u5ddd\u904a\u6c34\u5730\u5730\u8cea\u8abf\u67fb\u696d\u52d9","client_name":"\u56fd\u571f\u4ea4\u901a\u7701\u5317\u9678\u5730\u65b9\u6574\u5099\u5c40\u5343\u66f2\u5ddd\u6cb3\u5ddd\u4e8b\u52d9\u6240","boring_xml_url":47,"boring_view_url":1,"soilmap_view_url":null,"soiltest_xml_url":47,"soiltest_view_url":47},{"id":578888,"code":"NGIC202206144-0004","latitude":"36.521111111111","longitude":"138.11194444444","source_code":"","project_name":"\u4fe1\u6fc3\u5ddd\u6c34\u7cfb\u5343\u66f2\u5ddd\u904a\u6c34\u5730\u4e8b\u696d","survey_name":"\u4ee4\u548c4\u5e74\u5ea6\u5343\u66f2\u5ddd\u904a\u6c34\u5730\u5730\u8cea\u8abf\u67fb\u696d\u52d9","client_name":"\u56fd\u571f\u4ea4\u901a\u7701\u5317\u9678\u5730\u65b9\u6574\u5099\u5c40\u5343\u66f2\u5ddd\u6cb3\u5ddd\u4e8b\u52d9\u6240","boring_xml_url":47,"boring_view_url":1,"soilmap_view_url":null,"soiltest_xml_url":47,"soiltest_view_url":47},{"id":578887,"code":"NGIC202206144-0003","latitude":"36.523333333333","longitude":"138.11111111111","source_code":"","project_name":"\u4fe1\u6fc3\u5ddd\u6c34\u7cfb\u5343\u66f2\u5ddd\u904a\u6c34\u5730\u4e8b\u696d","survey_name":"\u4ee4\u548c4\u5e74\u5ea6\u5343\u66f2\u5ddd\u904a\u6c34\u5730\u5730\u8cea\u8abf\u67fb\u696d\u52d9","client_name":"\u56fd\u571f\u4ea4\u901a\u7701\u5317\u9678\u5730\u65b9\u6574\u5099\u5c40\u5343\u66f2\u5ddd\u6cb3\u5ddd\u4e8b\u52d9\u6240","boring_xml_url":47,"boring_view_url":1,"soilmap_view_url":null,"soiltest_xml_url":47,"soiltest_view_url":47},{"id":578886,"code":"NGIC202206144-0002","latitude":"36.527222222222","longitude":"138.10944444444","source_code":"","project_name":"\u4fe1\u6fc3\u5ddd\u6c34\u7cfb\u5343\u66f2\u5ddd\u904a\u6c34\u5730\u4e8b\u696d","survey_name":"\u4ee4\u548c4\u5e74\u5ea6\u5343\u66f2\u5ddd\u904a\u6c34\u5730\u5730\u8cea\u8abf\u67fb\u696d\u52d9","client_name":"\u56fd\u571f\u4ea4\u901a\u7701\u5317\u9678\u5730\u65b9\u6574\u5099\u5c40\u5343\u66f2\u5ddd\u6cb3\u5ddd\u4e8b\u52d9\u6240","boring_xml_url":47,"boring_view_url":1,"soilmap_view_url":null,"soiltest_xml_url":47,"soiltest_view_url":47},{"id":578885,"code":"NGIC202206144-0001","latitude":"36.529166666667","longitude":"138.10972222222","source_code":"","project_name":"\u4fe1\u6fc3\u5ddd\u6c34\u7cfb\u5343\u66f2\u5ddd\u904a\u6c34\u5730\u4e8b\u696d","survey_name":"\u4ee4\u548c4\u5e74\u5ea6\u5343\u66f2\u5ddd\u904a\u6c34\u5730\u5730\u8cea\u8abf\u67fb\u696d\u52d9","client_name":"\u56fd\u571f\u4ea4\u901a\u7701\u5317\u9678\u5730\u65b9\u6574\u5099\u5c40\u5343\u66f2\u5ddd\u6cb3\u5ddd\u4e8b\u52d9\u6240","boring_xml_url":47,"boring_view_url":1,"soilmap_view_url":null,"soiltest_xml_url":47,"soiltest_view_url":47},{"id":578841,"code":"NGIC202206090-0001","latitude":"37.855694444444","longitude":"139.12836111111","source_code":"","project_name":"\u56fd\u905349\u53f7\u6a2a\u8d8a\u4ea4\u5dee\u70b9\u5730\u8cea\u8abf\u67fb","survey_name":"R4\u65b0\u6f5f\u56fd\u9053\u7ba1\u5185\u5730\u8cea\u8abf\u67fb\u696d\u52d9","client_name":"\u56fd\u571f\u4ea4\u901a\u7701\u5317\u9678\u5730\u65b9\u6574\u5099\u5c40\u65b0\u6f5f\u56fd\u9053\u4e8b\u52d9\u6240","boring_xml_url":47,"boring_view_url":1,"soilmap_view_url":null,"soiltest_xml_url":47,"soiltest_view_url":47},{"id":578778,"code":"NGIC202205877-0011","latitude":"32.769431111111","longitude":"130.68861972222","source_code":"","project_name":"","survey_name":"\u4ee4\u548c4\u5e74\u5ea6\u767d\u5ddd\u4e0b\u6d41\u90e8\u5730\u8cea\u8abf\u67fb\u696d\u52d9","client_name":"\u56fd\u571f\u4ea4\u901a\u7701\u4e5d\u5dde\u5730\u65b9\u6574\u5099\u5c40\u718a\u672c\u6cb3\u5ddd\u56fd\u9053\u4e8b\u52d9\u6240\u8abf\u67fb\u7b2c\u4e00\u8ab2","boring_xml_url":47,"boring_view_url":1,"soilmap_view_url":null,"soiltest_xml_url":47,"soiltest_view_url":47}]}}