{"header":{"xyz":{"source":[],"mosaic":false},"page":25,"raw":{"soiltest_result":"0","bbox":"57.598333,109.544722,1.933333,163.806111","page":"25"},"conditions":{"soiltest_result":0,"north":57.598333,"west":109.544722,"south":1.933333,"east":163.806111},"success":true,"message":""},"data":{"meta":{"total":212844,"page":25,"pages":7095,"count":30},"values":[{"id":702279,"code":"NGIC202305928-0003","latitude":"33.698880694444","longitude":"132.70606458333","source_code":"","project_name":"","survey_name":"\u4ee4\u548c4-5\u5e74\u5ea6\u677e\u4e8c\u7ba1\u5185\u9632\u707d\u70b9\u691c\u696d\u52d9","client_name":"\u56fd\u571f\u4ea4\u901a\u7701\u56db\u56fd\u5730\u65b9\u6574\u5099\u5c40\u677e\u5c71\u6cb3\u5ddd\u56fd\u9053\u4e8b\u52d9\u6240","boring_xml_url":47,"boring_view_url":1,"soilmap_view_url":null,"soiltest_xml_url":0,"soiltest_view_url":0},{"id":702278,"code":"NGIC202305928-0002","latitude":"33.699433833333","longitude":"132.70610466667","source_code":"","project_name":"","survey_name":"\u4ee4\u548c4-5\u5e74\u5ea6\u677e\u4e8c\u7ba1\u5185\u9632\u707d\u70b9\u691c\u696d\u52d9","client_name":"\u56fd\u571f\u4ea4\u901a\u7701\u56db\u56fd\u5730\u65b9\u6574\u5099\u5c40\u677e\u5c71\u6cb3\u5ddd\u56fd\u9053\u4e8b\u52d9\u6240","boring_xml_url":47,"boring_view_url":1,"soilmap_view_url":null,"soiltest_xml_url":0,"soiltest_view_url":0},{"id":702277,"code":"NGIC202305928-0001","latitude":"33.699276472222","longitude":"132.70597016667","source_code":"","project_name":"","survey_name":"\u4ee4\u548c4-5\u5e74\u5ea6\u677e\u4e8c\u7ba1\u5185\u9632\u707d\u70b9\u691c\u696d\u52d9","client_name":"\u56fd\u571f\u4ea4\u901a\u7701\u56db\u56fd\u5730\u65b9\u6574\u5099\u5c40\u677e\u5c71\u6cb3\u5ddd\u56fd\u9053\u4e8b\u52d9\u6240","boring_xml_url":47,"boring_view_url":1,"soilmap_view_url":null,"soiltest_xml_url":0,"soiltest_view_url":0},{"id":702276,"code":"NGIC202306143-0008","latitude":"35.596345305556","longitude":"138.00083986111","source_code":"","project_name":"","survey_name":"\u4ee4\u548c5\u5e74\u5ea6\u5c0f\u6e0b\u30c0\u30e0\u7ba1\u5185\u5730\u8cea\u8abf\u67fb\u696d\u52d9","client_name":"\u56fd\u571f\u4ea4\u901a\u7701\u4e2d\u90e8\u5730\u65b9\u6574\u5099\u5c40\u5929\u7adc\u5ddd\u30c0\u30e0\u7d71\u5408\u7ba1\u7406\u4e8b\u52d9\u6240","boring_xml_url":47,"boring_view_url":1,"soilmap_view_url":null,"soiltest_xml_url":0,"soiltest_view_url":0},{"id":702275,"code":"NGIC202306143-0007","latitude":"35.596716","longitude":"138.00036211111","source_code":"","project_name":"","survey_name":"\u4ee4\u548c5\u5e74\u5ea6\u5c0f\u6e0b\u30c0\u30e0\u7ba1\u5185\u5730\u8cea\u8abf\u67fb\u696d\u52d9","client_name":"\u56fd\u571f\u4ea4\u901a\u7701\u4e2d\u90e8\u5730\u65b9\u6574\u5099\u5c40\u5929\u7adc\u5ddd\u30c0\u30e0\u7d71\u5408\u7ba1\u7406\u4e8b\u52d9\u6240","boring_xml_url":47,"boring_view_url":1,"soilmap_view_url":null,"soiltest_xml_url":0,"soiltest_view_url":0},{"id":702274,"code":"NGIC202306143-0006","latitude":"35.596264416667","longitude":"138.00055297222","source_code":"","project_name":"","survey_name":"\u4ee4\u548c5\u5e74\u5ea6\u5c0f\u6e0b\u30c0\u30e0\u7ba1\u5185\u5730\u8cea\u8abf\u67fb\u696d\u52d9","client_name":"\u56fd\u571f\u4ea4\u901a\u7701\u4e2d\u90e8\u5730\u65b9\u6574\u5099\u5c40\u5929\u7adc\u5ddd\u30c0\u30e0\u7d71\u5408\u7ba1\u7406\u4e8b\u52d9\u6240","boring_xml_url":47,"boring_view_url":1,"soilmap_view_url":null,"soiltest_xml_url":0,"soiltest_view_url":0},{"id":702273,"code":"NGIC202306143-0005","latitude":"35.595842666667","longitude":"138.00073122222","source_code":"","project_name":"","survey_name":"\u4ee4\u548c5\u5e74\u5ea6\u5c0f\u6e0b\u30c0\u30e0\u7ba1\u5185\u5730\u8cea\u8abf\u67fb\u696d\u52d9","client_name":"\u56fd\u571f\u4ea4\u901a\u7701\u4e2d\u90e8\u5730\u65b9\u6574\u5099\u5c40\u5929\u7adc\u5ddd\u30c0\u30e0\u7d71\u5408\u7ba1\u7406\u4e8b\u52d9\u6240","boring_xml_url":47,"boring_view_url":1,"soilmap_view_url":null,"soiltest_xml_url":0,"soiltest_view_url":0},{"id":702272,"code":"NGIC202306143-0004","latitude":"35.599342805556","longitude":"138.00706716667","source_code":"","project_name":"","survey_name":"\u4ee4\u548c5\u5e74\u5ea6\u5c0f\u6e0b\u30c0\u30e0\u7ba1\u5185\u5730\u8cea\u8abf\u67fb\u696d\u52d9","client_name":"\u56fd\u571f\u4ea4\u901a\u7701\u4e2d\u90e8\u5730\u65b9\u6574\u5099\u5c40\u5929\u7adc\u5ddd\u30c0\u30e0\u7d71\u5408\u7ba1\u7406\u4e8b\u52d9\u6240","boring_xml_url":47,"boring_view_url":1,"soilmap_view_url":null,"soiltest_xml_url":0,"soiltest_view_url":0},{"id":702271,"code":"NGIC202306143-0003","latitude":"35.59920125","longitude":"138.00775008333","source_code":"","project_name":"","survey_name":"\u4ee4\u548c5\u5e74\u5ea6\u5c0f\u6e0b\u30c0\u30e0\u7ba1\u5185\u5730\u8cea\u8abf\u67fb\u696d\u52d9","client_name":"\u56fd\u571f\u4ea4\u901a\u7701\u4e2d\u90e8\u5730\u65b9\u6574\u5099\u5c40\u5929\u7adc\u5ddd\u30c0\u30e0\u7d71\u5408\u7ba1\u7406\u4e8b\u52d9\u6240","boring_xml_url":47,"boring_view_url":1,"soilmap_view_url":null,"soiltest_xml_url":0,"soiltest_view_url":0},{"id":702270,"code":"NGIC202306143-0002","latitude":"35.599524305556","longitude":"138.00723983333","source_code":"","project_name":"","survey_name":"\u4ee4\u548c5\u5e74\u5ea6\u5c0f\u6e0b\u30c0\u30e0\u7ba1\u5185\u5730\u8cea\u8abf\u67fb\u696d\u52d9","client_name":"\u56fd\u571f\u4ea4\u901a\u7701\u4e2d\u90e8\u5730\u65b9\u6574\u5099\u5c40\u5929\u7adc\u5ddd\u30c0\u30e0\u7d71\u5408\u7ba1\u7406\u4e8b\u52d9\u6240","boring_xml_url":47,"boring_view_url":1,"soilmap_view_url":null,"soiltest_xml_url":0,"soiltest_view_url":0},{"id":702269,"code":"NGIC202306143-0001","latitude":"35.599778333333","longitude":"138.00683880556","source_code":"","project_name":"","survey_name":"\u4ee4\u548c5\u5e74\u5ea6\u5c0f\u6e0b\u30c0\u30e0\u7ba1\u5185\u5730\u8cea\u8abf\u67fb\u696d\u52d9","client_name":"\u56fd\u571f\u4ea4\u901a\u7701\u4e2d\u90e8\u5730\u65b9\u6574\u5099\u5c40\u5929\u7adc\u5ddd\u30c0\u30e0\u7d71\u5408\u7ba1\u7406\u4e8b\u52d9\u6240","boring_xml_url":47,"boring_view_url":1,"soilmap_view_url":null,"soiltest_xml_url":0,"soiltest_view_url":0},{"id":702214,"code":"NGIC202305898-0002","latitude":"33.289141666667","longitude":"129.88048611111","source_code":"","project_name":"","survey_name":"\u4ee4\u548c5\u5e74\u5ea6\u4f50\u8cc0\u56fd\u9053\u6539\u7bc9\u4e8b\u696d\u5730\u3059\u3079\u308a\u8abf\u67fb\u696d\u52d9","client_name":"\u56fd\u571f\u4ea4\u901a\u7701\u4e5d\u5dde\u5730\u65b9\u6574\u5099\u5c40\u4f50\u8cc0\u56fd\u9053\u4e8b\u52d9\u6240","boring_xml_url":47,"boring_view_url":1,"soilmap_view_url":null,"soiltest_xml_url":0,"soiltest_view_url":0},{"id":702213,"code":"NGIC202305898-0001","latitude":"33.289747222222","longitude":"129.87998888889","source_code":"","project_name":"","survey_name":"\u4ee4\u548c5\u5e74\u5ea6\u4f50\u8cc0\u56fd\u9053\u6539\u7bc9\u4e8b\u696d\u5730\u3059\u3079\u308a\u8abf\u67fb\u696d\u52d9","client_name":"\u56fd\u571f\u4ea4\u901a\u7701\u4e5d\u5dde\u5730\u65b9\u6574\u5099\u5c40\u4f50\u8cc0\u56fd\u9053\u4e8b\u52d9\u6240","boring_xml_url":47,"boring_view_url":1,"soilmap_view_url":null,"soiltest_xml_url":0,"soiltest_view_url":0},{"id":702210,"code":"NGIC202305888-0005","latitude":"34.324261111111","longitude":"134.04341111111","source_code":"","project_name":"","survey_name":"\u4ee4\u548c5\u5e74\u5ea6\u9999\u5ddd\u7ba1\u5185\u9632\u707d\u70b9\u691c\u5916\u8a2d\u8a08\u696d\u52d9","client_name":"\u56fd\u571f\u4ea4\u901a\u7701\u56db\u56fd\u5730\u65b9\u6574\u5099\u5c40\u9999\u5ddd\u6cb3\u5ddd\u56fd\u9053\u4e8b\u52d9\u6240","boring_xml_url":47,"boring_view_url":1,"soilmap_view_url":null,"soiltest_xml_url":47,"soiltest_view_url":47},{"id":702209,"code":"NGIC202305888-0004","latitude":"34.228172222222","longitude":"134.38635555556","source_code":"","project_name":"","survey_name":"\u4ee4\u548c5\u5e74\u5ea6\u9999\u5ddd\u7ba1\u5185\u9632\u707d\u70b9\u691c\u5916\u8a2d\u8a08\u696d\u52d9","client_name":"\u56fd\u571f\u4ea4\u901a\u7701\u56db\u56fd\u5730\u65b9\u6574\u5099\u5c40\u9999\u5ddd\u6cb3\u5ddd\u56fd\u9053\u4e8b\u52d9\u6240","boring_xml_url":47,"boring_view_url":1,"soilmap_view_url":null,"soiltest_xml_url":47,"soiltest_view_url":47},{"id":702208,"code":"NGIC202305888-0003","latitude":"34.228625","longitude":"134.38615555556","source_code":"","project_name":"","survey_name":"\u4ee4\u548c5\u5e74\u5ea6\u9999\u5ddd\u7ba1\u5185\u9632\u707d\u70b9\u691c\u5916\u8a2d\u8a08\u696d\u52d9","client_name":"\u56fd\u571f\u4ea4\u901a\u7701\u56db\u56fd\u5730\u65b9\u6574\u5099\u5c40\u9999\u5ddd\u6cb3\u5ddd\u56fd\u9053\u4e8b\u52d9\u6240","boring_xml_url":47,"boring_view_url":1,"soilmap_view_url":null,"soiltest_xml_url":47,"soiltest_view_url":47},{"id":702207,"code":"NGIC202305888-0002","latitude":"34.228172222222","longitude":"134.38635555556","source_code":"","project_name":"","survey_name":"\u4ee4\u548c5\u5e74\u5ea6\u9999\u5ddd\u7ba1\u5185\u9632\u707d\u70b9\u691c\u5916\u8a2d\u8a08\u696d\u52d9","client_name":"\u56fd\u571f\u4ea4\u901a\u7701\u56db\u56fd\u5730\u65b9\u6574\u5099\u5c40\u9999\u5ddd\u6cb3\u5ddd\u56fd\u9053\u4e8b\u52d9\u6240","boring_xml_url":47,"boring_view_url":1,"soilmap_view_url":null,"soiltest_xml_url":0,"soiltest_view_url":0},{"id":702206,"code":"NGIC202305888-0001","latitude":"34.228091666667","longitude":"134.38638888889","source_code":"","project_name":"","survey_name":"\u4ee4\u548c5\u5e74\u5ea6\u9999\u5ddd\u7ba1\u5185\u9632\u707d\u70b9\u691c\u5916\u8a2d\u8a08\u696d\u52d9","client_name":"\u56fd\u571f\u4ea4\u901a\u7701\u56db\u56fd\u5730\u65b9\u6574\u5099\u5c40\u9999\u5ddd\u6cb3\u5ddd\u56fd\u9053\u4e8b\u52d9\u6240","boring_xml_url":47,"boring_view_url":1,"soilmap_view_url":null,"soiltest_xml_url":0,"soiltest_view_url":0},{"id":702183,"code":"NGIC202305874-0001","latitude":"26.212972222222","longitude":"127.64677777778","source_code":"","project_name":"\u90a3\u8987\u7a7a\u6e2f\u5317\u5074\u5834\u5468\u9053\u8def\u62e1\u5e45\u5b9f\u65bd\u8a2d\u8a08\u696d\u52d9","survey_name":"\u90a3\u8987\u7a7a\u6e2f\u5317\u5074\u5834\u5468\u9053\u8def\u62e1\u5e45\u5b9f\u65bd\u8a2d\u8a08\u696d\u52d9","client_name":"\u56fd\u571f\u4ea4\u901a\u7701\u5927\u962a\u822a\u7a7a\u5c40","boring_xml_url":47,"boring_view_url":1,"soilmap_view_url":null,"soiltest_xml_url":47,"soiltest_view_url":47},{"id":702085,"code":"NGIC202305846-0009","latitude":"35.373888583333","longitude":"132.78110602778","source_code":"","project_name":"","survey_name":"\u4ee4\u548c5\u5e74\u5ea6 \u51fa\u96f2\u30d0\u30a4\u30d1\u30b9\u5730\u8cea\u8abf\u67fb\u696d\u52d9","client_name":"\u56fd\u571f\u4ea4\u901a\u7701\u4e2d\u56fd\u5730\u65b9\u6574\u5099\u5c40\u677e\u6c5f\u56fd\u9053\u4e8b\u52d9\u6240","boring_xml_url":47,"boring_view_url":1,"soilmap_view_url":null,"soiltest_xml_url":47,"soiltest_view_url":47},{"id":702084,"code":"NGIC202305846-0008","latitude":"35.373743694444","longitude":"132.78194683333","source_code":"","project_name":"","survey_name":"\u4ee4\u548c5\u5e74\u5ea6 \u51fa\u96f2\u30d0\u30a4\u30d1\u30b9\u5730\u8cea\u8abf\u67fb\u696d\u52d9","client_name":"\u56fd\u571f\u4ea4\u901a\u7701\u4e2d\u56fd\u5730\u65b9\u6574\u5099\u5c40\u677e\u6c5f\u56fd\u9053\u4e8b\u52d9\u6240","boring_xml_url":47,"boring_view_url":1,"soilmap_view_url":null,"soiltest_xml_url":0,"soiltest_view_url":0},{"id":702083,"code":"NGIC202305846-0007","latitude":"35.373600527778","longitude":"132.78279844444","source_code":"","project_name":"","survey_name":"\u4ee4\u548c5\u5e74\u5ea6 \u51fa\u96f2\u30d0\u30a4\u30d1\u30b9\u5730\u8cea\u8abf\u67fb\u696d\u52d9","client_name":"\u56fd\u571f\u4ea4\u901a\u7701\u4e2d\u56fd\u5730\u65b9\u6574\u5099\u5c40\u677e\u6c5f\u56fd\u9053\u4e8b\u52d9\u6240","boring_xml_url":47,"boring_view_url":1,"soilmap_view_url":null,"soiltest_xml_url":0,"soiltest_view_url":0},{"id":702082,"code":"NGIC202305846-0006","latitude":"35.373528944444","longitude":"132.78322425","source_code":"","project_name":"","survey_name":"\u4ee4\u548c5\u5e74\u5ea6 \u51fa\u96f2\u30d0\u30a4\u30d1\u30b9\u5730\u8cea\u8abf\u67fb\u696d\u52d9","client_name":"\u56fd\u571f\u4ea4\u901a\u7701\u4e2d\u56fd\u5730\u65b9\u6574\u5099\u5c40\u677e\u6c5f\u56fd\u9053\u4e8b\u52d9\u6240","boring_xml_url":47,"boring_view_url":1,"soilmap_view_url":null,"soiltest_xml_url":47,"soiltest_view_url":47},{"id":702081,"code":"NGIC202305846-0005","latitude":"35.373456833333","longitude":"132.78365005556","source_code":"","project_name":"","survey_name":"\u4ee4\u548c5\u5e74\u5ea6 \u51fa\u96f2\u30d0\u30a4\u30d1\u30b9\u5730\u8cea\u8abf\u67fb\u696d\u52d9","client_name":"\u56fd\u571f\u4ea4\u901a\u7701\u4e2d\u56fd\u5730\u65b9\u6574\u5099\u5c40\u677e\u6c5f\u56fd\u9053\u4e8b\u52d9\u6240","boring_xml_url":47,"boring_view_url":1,"soilmap_view_url":null,"soiltest_xml_url":0,"soiltest_view_url":0},{"id":702080,"code":"NGIC202305846-0004","latitude":"35.375001277778","longitude":"132.77440319444","source_code":"","project_name":"","survey_name":"\u4ee4\u548c5\u5e74\u5ea6 \u51fa\u96f2\u30d0\u30a4\u30d1\u30b9\u5730\u8cea\u8abf\u67fb\u696d\u52d9","client_name":"\u56fd\u571f\u4ea4\u901a\u7701\u4e2d\u56fd\u5730\u65b9\u6574\u5099\u5c40\u677e\u6c5f\u56fd\u9053\u4e8b\u52d9\u6240","boring_xml_url":47,"boring_view_url":1,"soilmap_view_url":null,"soiltest_xml_url":47,"soiltest_view_url":47},{"id":702079,"code":"NGIC202305846-0003","latitude":"35.374815555556","longitude":"132.77564533333","source_code":"","project_name":"","survey_name":"\u4ee4\u548c5\u5e74\u5ea6 \u51fa\u96f2\u30d0\u30a4\u30d1\u30b9\u5730\u8cea\u8abf\u67fb\u696d\u52d9","client_name":"\u56fd\u571f\u4ea4\u901a\u7701\u4e2d\u56fd\u5730\u65b9\u6574\u5099\u5c40\u677e\u6c5f\u56fd\u9053\u4e8b\u52d9\u6240","boring_xml_url":47,"boring_view_url":1,"soilmap_view_url":null,"soiltest_xml_url":47,"soiltest_view_url":47},{"id":702078,"code":"NGIC202305846-0002","latitude":"35.374608388889","longitude":"132.77708313889","source_code":"","project_name":"","survey_name":"\u4ee4\u548c5\u5e74\u5ea6 \u51fa\u96f2\u30d0\u30a4\u30d1\u30b9\u5730\u8cea\u8abf\u67fb\u696d\u52d9","client_name":"\u56fd\u571f\u4ea4\u901a\u7701\u4e2d\u56fd\u5730\u65b9\u6574\u5099\u5c40\u677e\u6c5f\u56fd\u9053\u4e8b\u52d9\u6240","boring_xml_url":47,"boring_view_url":1,"soilmap_view_url":null,"soiltest_xml_url":47,"soiltest_view_url":47},{"id":702077,"code":"NGIC202305846-0001","latitude":"35.374454083333","longitude":"132.77759047222","source_code":"","project_name":"","survey_name":"\u4ee4\u548c5\u5e74\u5ea6 \u51fa\u96f2\u30d0\u30a4\u30d1\u30b9\u5730\u8cea\u8abf\u67fb\u696d\u52d9","client_name":"\u56fd\u571f\u4ea4\u901a\u7701\u4e2d\u56fd\u5730\u65b9\u6574\u5099\u5c40\u677e\u6c5f\u56fd\u9053\u4e8b\u52d9\u6240","boring_xml_url":47,"boring_view_url":1,"soilmap_view_url":null,"soiltest_xml_url":47,"soiltest_view_url":47},{"id":702073,"code":"NGIC202305695-0004","latitude":"34.5785575","longitude":"135.66920222222","source_code":"","project_name":"","survey_name":"\u9632\u707d\u70b9\u691c\u696d\u52d9","client_name":"\u56fd\u571f\u4ea4\u901a\u7701\u8fd1\u757f\u5730\u65b9\u6574\u5099\u5c40\u5927\u962a\u56fd\u9053\u4e8b\u52d9\u6240","boring_xml_url":47,"boring_view_url":1,"soilmap_view_url":null,"soiltest_xml_url":0,"soiltest_view_url":0},{"id":702072,"code":"NGIC202305695-0003","latitude":"34.578735277778","longitude":"135.66958166667","source_code":"","project_name":"","survey_name":"\u9632\u707d\u70b9\u691c\u696d\u52d9","client_name":"\u56fd\u571f\u4ea4\u901a\u7701\u8fd1\u757f\u5730\u65b9\u6574\u5099\u5c40\u5927\u962a\u56fd\u9053\u4e8b\u52d9\u6240","boring_xml_url":47,"boring_view_url":1,"soilmap_view_url":null,"soiltest_xml_url":0,"soiltest_view_url":0}]}}